catboxpy/__init__.py
catboxpy/album.py
catboxpy/async_album.py
catboxpy/async_catbox.py
catboxpy/catbox.py
catboxpy/litterbox.py
catboxpy-0.1.1.1.dist-info/licenses/LICENSE
catboxpy-0.1.1.1.dist-info/METADATA
catboxpy-0.1.1.1.dist-info/WHEEL
catboxpy-0.1.1.1.dist-info/top_level.txt
catboxpy-0.1.1.1.dist-info/RECORD
