Metadata-Version: 2.4
Name: catboxpy
Version: 0.1.1.1
Summary: A Python wrapper for the Catbox.moe and Litterbox api with Async features
Home-page: https://github.com/anshonweb/catboxpy
Author: anshonweb
Author-email: ansh.a.3112@gmail.com
License: MIT
Keywords: catbox api python wrapper async litterbox
License-File: LICENSE
Requires-Dist: httpx>=0.24.0
Requires-Dist: requests
Dynamic: author
Dynamic: author-email
Dynamic: description
Dynamic: description-content-type
Dynamic: home-page
Dynamic: keywords
Dynamic: license
Dynamic: license-file
Dynamic: requires-dist
Dynamic: summary
